hmd_lang_deployment/__init__.py
hmd_lang_deployment/change_set.py
hmd_lang_deployment/change_set_deployment.py
hmd_lang_deployment/change_set_deployment_has_change_set.py
hmd_lang_deployment/change_set_deployment_has_change_set_env_deployment.py
hmd_lang_deployment/change_set_deployment_has_deployment_set.py
hmd_lang_deployment/change_set_env_deployment.py
hmd_lang_deployment/change_set_env_deployment_has_environment.py
hmd_lang_deployment/change_set_env_deployment_has_environment_action_execution.py
hmd_lang_deployment/change_set_env_deployment_has_repo_instance_deployment.py
hmd_lang_deployment/deployment_set.py
hmd_lang_deployment/environment.py
hmd_lang_deployment/environment_action.py
hmd_lang_deployment/environment_action_execution.py
hmd_lang_deployment/environment_action_execution_has_environment_action_version.py
hmd_lang_deployment/environment_action_has_environment_action_version.py
hmd_lang_deployment/environment_action_version.py
hmd_lang_deployment/environment_has_repo_instance.py
hmd_lang_deployment/external_artifact.py
hmd_lang_deployment/hmd_lang_deployment_client.py
hmd_lang_deployment/repo_class.py
hmd_lang_deployment/repo_class_has_repo_class_version.py
hmd_lang_deployment/repo_class_version.py
hmd_lang_deployment/repo_class_version_has_external_artifact.py
hmd_lang_deployment/repo_class_version_has_repo_class_version_notes.py
hmd_lang_deployment/repo_class_version_notes.py
hmd_lang_deployment/repo_class_version_req_repo_class.py
hmd_lang_deployment/repo_instance.py
hmd_lang_deployment/repo_instance_deployment.py
hmd_lang_deployment/repo_instance_deployment_has_repo_class_version.py
hmd_lang_deployment/repo_instance_has_repo_instance_deployment.py
hmd_lang_deployment/repo_instance_isa_repo_class.py
hmd_lang_deployment/repo_instance_req_repo_instance.py
hmd_lang_deployment/timestamp_record.py
hmd_lang_deployment/schemas/hmd_lang_deployment/change_set.hms
hmd_lang_deployment/schemas/hmd_lang_deployment/change_set.ui.hms
hmd_lang_deployment-0.1.78.dist-info/METADATA
hmd_lang_deployment-0.1.78.dist-info/WHEEL
hmd_lang_deployment-0.1.78.dist-info/top_level.txt
hmd_lang_deployment-0.1.78.dist-info/RECORD
