Metadata-Version: 2.1
Name: hmd-lang-deployment
Version: 0.1.78
Summary: Language pack for deployment model.
Home-page: UNKNOWN
Author: Jim Majure
Author-email: jim.majure@hmdlabs.io
License: Apache 2.0
Platform: UNKNOWN
Requires-Dist: hmd-meta-types
Requires-Dist: hmd-schema-loader
